[
  {
    "name": "Login___fa",
    "path": "/Login",
    "component": "F:\\\\blog\\\\frontend\\\\pages\\\\Login\\\\index.vue",
    "chunkName": "pages/Login/index"
  },
  {
    "name": "profile___fa",
    "path": "/profile",
    "component": "F:\\\\blog\\\\frontend\\\\pages\\\\profile\\\\index.vue",
    "chunkName": "pages/profile/index"
  },
  {
    "name": "Register___fa",
    "path": "/Register",
    "component": "F:\\\\blog\\\\frontend\\\\pages\\\\Register\\\\index.vue",
    "chunkName": "pages/Register/index"
  },
  {
    "name": "index___fa",
    "path": "/",
    "component": "F:\\\\blog\\\\frontend\\\\pages\\\\index.vue",
    "chunkName": "pages/index"
  }
]
